stalimet
